[{
    "Rk": 1,
    "team_name": "Angels",
    "Lg": "AL",
    "year": 2004,
    "W": 92,
    "L": 70,
    "W-L%": 0.568,
    "R": 5.2,
    "RA": 4.5,
    "Rdiff": 0.6,
    "SOS": 0.1,
    "SRS": 0.7,
    "pythWL": "91-71",
    "Luck": 1,
    "Inter": "7-11",
    "Home": "45-36",
    "Road": "47-34",
    "ExInn": "4-6",
    "1Run": "19-21",
    "vRHP": "58-53",
    "vLHP": "34-17",
    "≥": {
        "500": "43-43"
    },
    "<": {
        "500": "49-27"
    },
    "payroll": 101084667,
    "team_waa": 7.2,
    "playoffs": true,
    "championship": false
}, {
    "Rk": 2,
    "team_name": "Diamondbacks",
    "Lg": "NL",
    "year": 2004,
    "W": 51,
    "L": 111,
    "W-L%": 0.315,
    "R": 3.8,
    "RA": 5.5,
    "Rdiff": -1.8,
    "SOS": 0,
    "SRS": -1.7,
    "pythWL": "54-108",
    "Luck": -3,
    "Inter": "6-12",
    "Home": "29-52",
    "Road": "22-59",
    "ExInn": "6-8",
    "1Run": "15-31",
    "vRHP": "38-70",
    "vLHP": "13-41",
    "≥": {
        "500": "30-70"
    },
    "<": {
        "500": "21-41"
    },
    "payroll": 70204984,
    "team_waa": -22.6,
    "playoffs": false,
    "championship": false
}, {
    "Rk": 3,
    "team_name": "Braves",
    "Lg": "NL",
    "year": 2004,
    "W": 96,
    "L": 66,
    "W-L%": 0.593,
    "R": 5,
    "RA": 4.1,
    "Rdiff": 0.8,
    "SOS": -0.1,
    "SRS": 0.7,
    "pythWL": "95-67",
    "Luck": 1,
    "Inter": "8-10",
    "Home": "49-32",
    "Road": "47-34",
    "ExInn": "7-8",
    "1Run": "27-17",
    "vRHP": "62-47",
    "vLHP": "34-19",
    "≥": {
        "500": "46-36"
    },
    "<": {
        "500": "50-30"
    },
    "payroll": 88507788,
    "team_waa": 12.5,
    "playoffs": true,
    "championship": false
}, {
    "Rk": 4,
    "team_name": "Orioles",
    "Lg": "AL",
    "year": 2004,
    "W": 78,
    "L": 84,
    "W-L%": 0.481,
    "R": 5.2,
    "RA": 5.1,
    "Rdiff": 0.1,
    "SOS": 0.1,
    "SRS": 0.1,
    "pythWL": "82-80",
    "Luck": -4,
    "Inter": "5-13",
    "Home": "38-43",
    "Road": "40-41",
    "ExInn": "6-7",
    "1Run": "15-22",
    "vRHP": "56-55",
    "vLHP": "22-29",
    "≥": {
        "500": "32-56"
    },
    "<": {
        "500": "46-28"
    },
    "payroll": 51212653,
    "team_waa": 2.3,
    "playoffs": false,
    "championship": false
}, {
    "Rk": 5,
    "team_name": "Redsox",
    "Lg": "AL",
    "year": 2004,
    "W": 98,
    "L": 64,
    "W-L%": 0.605,
    "R": 5.9,
    "RA": 4.7,
    "Rdiff": 1.1,
    "SOS": 0,
    "SRS": 1.1,
    "pythWL": "96-66",
    "Luck": 2,
    "Inter": "9-9",
    "Home": "55-26",
    "Road": "43-38",
    "ExInn": "6-6",
    "1Run": "16-18",
    "vRHP": "66-40",
    "vLHP": "32-24",
    "≥": {
        "500": "42-31"
    },
    "<": {
        "500": "56-33"
    },
    "payroll": 125208542,
    "team_waa": 17.9,
    "playoffs": true,
    "championship": true
}, {
    "Rk": 6,
    "team_name": "Cubs",
    "Lg": "NL",
    "year": 2004,
    "W": 89,
    "L": 73,
    "W-L%": 0.549,
    "R": 4.9,
    "RA": 4.1,
    "Rdiff": 0.8,
    "SOS": 0,
    "SRS": 0.7,
    "pythWL": "94-68",
    "Luck": -5,
    "Inter": "8-4",
    "Home": "45-37",
    "Road": "44-36",
    "ExInn": "10-9",
    "1Run": "19-30",
    "vRHP": "64-58",
    "vLHP": "25-15",
    "≥": {
        "500": "43-43"
    },
    "<": {
        "500": "46-30"
    },
    "payroll": 91101667,
    "team_waa": 16.7,
    "playoffs": false,
    "championship": false
}, {
    "Rk": 7,
    "team_name": "Whitesox",
    "Lg": "AL",
    "year": 2004,
    "W": 83,
    "L": 79,
    "W-L%": 0.512,
    "R": 5.3,
    "RA": 5.1,
    "Rdiff": 0.2,
    "SOS": 0,
    "SRS": 0.2,
    "pythWL": "84-78",
    "Luck": -1,
    "Inter": "8-10",
    "Home": "46-35",
    "Road": "37-44",
    "ExInn": "6-7",
    "1Run": "28-18",
    "vRHP": "62-44",
    "vLHP": "21-35",
    "≥": {
        "500": "33-41"
    },
    "<": {
        "500": "50-38"
    },
    "payroll": 65212500,
    "team_waa": 0.0,
    "playoffs": false,
    "championship": false
}, {
    "Rk": 8,
    "team_name": "Reds",
    "Lg": "NL",
    "year": 2004,
    "W": 76,
    "L": 86,
    "W-L%": 0.469,
    "R": 4.6,
    "RA": 5.6,
    "Rdiff": -1,
    "SOS": 0.1,
    "SRS": -0.9,
    "pythWL": "67-95",
    "Luck": 9,
    "Inter": "5-7",
    "Home": "40-41",
    "Road": "36-45",
    "ExInn": "12-7",
    "1Run": "25-20",
    "vRHP": "53-62",
    "vLHP": "23-24",
    "≥": {
        "500": "42-53"
    },
    "<": {
        "500": "34-33"
    },
    "payroll": 43067858,
    "team_waa": -16.0,
    "playoffs": false,
    "championship": false
}, {
    "Rk": 9,
    "team_name": "Indians",
    "Lg": "AL",
    "year": 2004,
    "W": 80,
    "L": 82,
    "W-L%": 0.494,
    "R": 5.3,
    "RA": 5.3,
    "Rdiff": 0,
    "SOS": 0,
    "SRS": 0,
    "pythWL": "81-81",
    "Luck": -1,
    "Inter": "10-8",
    "Home": "44-37",
    "Road": "36-45",
    "ExInn": "11-13",
    "1Run": "26-20",
    "vRHP": "56-48",
    "vLHP": "24-34",
    "≥": {
        "500": "37-47"
    },
    "<": {
        "500": "43-35"
    },
    "payroll": 34569300,
    "team_waa": 1.2,
    "playoffs": false,
    "championship": false
}, {
    "Rk": 10,
    "team_name": "Rockies",
    "Lg": "NL",
    "year": 2004,
    "W": 68,
    "L": 94,
    "W-L%": 0.42,
    "R": 5.1,
    "RA": 5.7,
    "Rdiff": -0.6,
    "SOS": -0.1,
    "SRS": -0.6,
    "pythWL": "73-89",
    "Luck": -5,
    "Inter": "8-10",
    "Home": "38-43",
    "Road": "30-51",
    "ExInn": "3-11",
    "1Run": "16-24",
    "vRHP": "42-73",
    "vLHP": "26-21",
    "≥": {
        "500": "39-62"
    },
    "<": {
        "500": "29-32"
    },
    "payroll": 64590403,
    "team_waa": -3.2,
    "playoffs": false,
    "championship": false
}, {
    "Rk": 11,
    "team_name": "Tigers",
    "Lg": "AL",
    "year": 2004,
    "W": 72,
    "L": 90,
    "W-L%": 0.444,
    "R": 5.1,
    "RA": 5.2,
    "Rdiff": -0.1,
    "SOS": 0,
    "SRS": -0.1,
    "pythWL": "79-83",
    "Luck": -7,
    "Inter": "9-9",
    "Home": "38-43",
    "Road": "34-47",
    "ExInn": "6-9",
    "1Run": "12-27",
    "vRHP": "48-52",
    "vLHP": "24-38",
    "≥": {
        "500": "39-49"
    },
    "<": {
        "500": "33-41"
    },
    "payroll": 46353554,
    "team_waa": -0.6,
    "playoffs": false,
    "championship": false
}, {
    "Rk": 12,
    "team_name": "Marlins",
    "Lg": "NL",
    "year": 2004,
    "W": 83,
    "L": 79,
    "W-L%": 0.512,
    "R": 4.4,
    "RA": 4.3,
    "Rdiff": 0.1,
    "SOS": -0.1,
    "SRS": 0,
    "pythWL": "83-79",
    "Luck": 0,
    "Inter": "7-11",
    "Home": "42-38",
    "Road": "41-41",
    "ExInn": "5-10",
    "1Run": "20-17",
    "vRHP": "58-59",
    "vLHP": "25-20",
    "≥": {
        "500": "36-45"
    },
    "<": {
        "500": "47-34"
    },
    "payroll": 42118042,
    "team_waa": 1.9,
    "playoffs": false,
    "championship": false
}, {
    "Rk": 13,
    "team_name": "Astros",
    "Lg": "NL",
    "year": 2004,
    "W": 92,
    "L": 70,
    "W-L%": 0.568,
    "R": 5,
    "RA": 4.3,
    "Rdiff": 0.6,
    "SOS": 0,
    "SRS": 0.6,
    "pythWL": "91-71",
    "Luck": 1,
    "Inter": "7-5",
    "Home": "48-33",
    "Road": "44-37",
    "ExInn": "3-7",
    "1Run": "24-18",
    "vRHP": "73-53",
    "vLHP": "19-17",
    "≥": {
        "500": "41-41"
    },
    "<": {
        "500": "51-29"
    },
    "payroll": 74666303,
    "team_waa": 10.0,
    "playoffs": true,
    "championship": false
}, {
    "Rk": 14,
    "team_name": "Royals",
    "Lg": "AL",
    "year": 2004,
    "W": 58,
    "L": 104,
    "W-L%": 0.358,
    "R": 4.4,
    "RA": 5.6,
    "Rdiff": -1.1,
    "SOS": 0.1,
    "SRS": -1,
    "pythWL": "64-98",
    "Luck": -6,
    "Inter": "6-12",
    "Home": "33-47",
    "Road": "25-57",
    "ExInn": "4-7",
    "1Run": "14-19",
    "vRHP": "36-79",
    "vLHP": "22-25",
    "≥": {
        "500": "25-62"
    },
    "<": {
        "500": "33-42"
    },
    "payroll": 47609000,
    "team_waa": -18.4,
    "playoffs": false,
    "championship": false
}, {
    "Rk": 15,
    "team_name": "Dodgers",
    "Lg": "NL",
    "year": 2004,
    "W": 93,
    "L": 69,
    "W-L%": 0.574,
    "R": 4.7,
    "RA": 4.2,
    "Rdiff": 0.5,
    "SOS": -0.2,
    "SRS": 0.3,
    "pythWL": "89-73",
    "Luck": 4,
    "Inter": "10-8",
    "Home": "49-32",
    "Road": "44-37",
    "ExInn": "11-3",
    "1Run": "32-16",
    "vRHP": "70-47",
    "vLHP": "23-22",
    "≥": {
        "500": "44-43"
    },
    "<": {
        "500": "49-26"
    },
    "payroll": 89694342,
    "team_waa": 10.9,
    "playoffs": true,
    "championship": false
}, {
    "Rk": 16,
    "team_name": "Brewers",
    "Lg": "NL",
    "year": 2004,
    "W": 67,
    "L": 94,
    "W-L%": 0.416,
    "R": 3.9,
    "RA": 4.7,
    "Rdiff": -0.8,
    "SOS": 0.1,
    "SRS": -0.7,
    "pythWL": "68-93",
    "Luck": -1,
    "Inter": "8-4",
    "Home": "36-45",
    "Road": "31-49",
    "ExInn": "5-12",
    "1Run": "18-20",
    "vRHP": "56-73",
    "vLHP": "11-21",
    "≥": {
        "500": "37-61"
    },
    "<": {
        "500": "30-33"
    },
    "payroll": 27518500,
    "team_waa": -6.9,
    "playoffs": false,
    "championship": false
}, {
    "Rk": 17,
    "team_name": "Twins",
    "Lg": "AL",
    "year": 2004,
    "W": 92,
    "L": 70,
    "W-L%": 0.568,
    "R": 4.8,
    "RA": 4.4,
    "Rdiff": 0.4,
    "SOS": -0.1,
    "SRS": 0.3,
    "pythWL": "87-75",
    "Luck": 5,
    "Inter": "11-7",
    "Home": "49-32",
    "Road": "43-38",
    "ExInn": "12-6",
    "1Run": "24-16",
    "vRHP": "62-47",
    "vLHP": "30-23",
    "≥": {
        "500": "28-29"
    },
    "<": {
        "500": "64-41"
    },
    "payroll": 53585000,
    "team_waa": 8.5,
    "playoffs": true,
    "championship": false
}, {
    "Rk": 18,
    "team_name": "Expos",
    "Lg": "NL",
    "year": 2004,
    "W": 67,
    "L": 95,
    "W-L%": 0.414,
    "R": 3.9,
    "RA": 4.7,
    "Rdiff": -0.8,
    "SOS": 0,
    "SRS": -0.8,
    "pythWL": "67-95",
    "Luck": 0,
    "Inter": "7-11",
    "Home": "35-45",
    "Road": "32-50",
    "ExInn": "5-8",
    "1Run": "16-30",
    "vRHP": "46-67",
    "vLHP": "21-28",
    "≥": {
        "500": "36-65"
    },
    "<": {
        "500": "31-30"
    },
    "payroll": 43197500,
    "team_waa": -11.5,
    "playoffs": false,
    "championship": false
}, {
    "Rk": 19,
    "team_name": "Mets",
    "Lg": "NL",
    "year": 2004,
    "W": 71,
    "L": 91,
    "W-L%": 0.438,
    "R": 4.2,
    "RA": 4.5,
    "Rdiff": -0.3,
    "SOS": 0,
    "SRS": -0.3,
    "pythWL": "76-86",
    "Luck": -5,
    "Inter": "10-8",
    "Home": "38-43",
    "Road": "33-48",
    "ExInn": "11-6",
    "1Run": "23-24",
    "vRHP": "54-64",
    "vLHP": "17-27",
    "≥": {
        "500": "38-65"
    },
    "<": {
        "500": "33-26"
    },
    "payroll": 100629303,
    "team_waa": -3.3,
    "playoffs": false,
    "championship": false
}, {
    "Rk": 20,
    "team_name": "Yankees",
    "Lg": "AL",
    "year": 2004,
    "W": 101,
    "L": 61,
    "W-L%": 0.624,
    "R": 5.5,
    "RA": 5,
    "Rdiff": 0.5,
    "SOS": 0,
    "SRS": 0.6,
    "pythWL": "89-73",
    "Luck": 12,
    "Inter": "10-8",
    "Home": "57-24",
    "Road": "44-37",
    "ExInn": "5-4",
    "1Run": "24-16",
    "vRHP": "65-49",
    "vLHP": "36-12",
    "≥": {
        "500": "35-30"
    },
    "<": {
        "500": "66-31"
    },
    "payroll": 182835513,
    "team_waa": 8.4,
    "playoffs": true,
    "championship": false
}, {
    "Rk": 21,
    "team_name": "Athletics",
    "Lg": "AL",
    "year": 2004,
    "W": 91,
    "L": 71,
    "W-L%": 0.562,
    "R": 4.9,
    "RA": 4.6,
    "Rdiff": 0.3,
    "SOS": 0.1,
    "SRS": 0.4,
    "pythWL": "86-76",
    "Luck": 5,
    "Inter": "10-8",
    "Home": "52-29",
    "Road": "39-42",
    "ExInn": "12-7",
    "1Run": "33-19",
    "vRHP": "62-53",
    "vLHP": "29-18",
    "≥": {
        "500": "39-46"
    },
    "<": {
        "500": "52-25"
    },
    "payroll": 59825167,
    "team_waa": 7.9,
    "playoffs": false,
    "championship": false
}, {
    "Rk": 22,
    "team_name": "Phillies",
    "Lg": "NL",
    "year": 2004,
    "W": 86,
    "L": 76,
    "W-L%": 0.531,
    "R": 5.2,
    "RA": 4.8,
    "Rdiff": 0.4,
    "SOS": -0.1,
    "SRS": 0.3,
    "pythWL": "86-76",
    "Luck": 0,
    "Inter": "9-9",
    "Home": "42-39",
    "Road": "44-37",
    "ExInn": "10-8",
    "1Run": "23-20",
    "vRHP": "63-53",
    "vLHP": "23-23",
    "≥": {
        "500": "38-45"
    },
    "<": {
        "500": "48-31"
    },
    "payroll": 93219167,
    "team_waa": 4.8,
    "playoffs": false,
    "championship": false
}, {
    "Rk": 23,
    "team_name": "Pirates",
    "Lg": "NL",
    "year": 2004,
    "W": 72,
    "L": 89,
    "W-L%": 0.447,
    "R": 4.2,
    "RA": 4.6,
    "Rdiff": -0.4,
    "SOS": 0,
    "SRS": -0.4,
    "pythWL": "74-87",
    "Luck": -2,
    "Inter": "2-10",
    "Home": "39-41",
    "Road": "33-48",
    "ExInn": "8-7",
    "1Run": "20-26",
    "vRHP": "58-68",
    "vLHP": "14-21",
    "≥": {
        "500": "35-62"
    },
    "<": {
        "500": "37-27"
    },
    "payroll": 32227929,
    "team_waa": -5.4,
    "playoffs": false,
    "championship": false
}, {
    "Rk": 24,
    "team_name": "Padres",
    "Lg": "NL",
    "year": 2004,
    "W": 87,
    "L": 75,
    "W-L%": 0.537,
    "R": 4.7,
    "RA": 4.4,
    "Rdiff": 0.4,
    "SOS": -0.2,
    "SRS": 0.2,
    "pythWL": "87-75",
    "Luck": 0,
    "Inter": "8-10",
    "Home": "42-39",
    "Road": "45-36",
    "ExInn": "7-4",
    "1Run": "25-15",
    "vRHP": "58-52",
    "vLHP": "29-23",
    "≥": {
        "500": "37-43"
    },
    "<": {
        "500": "50-32"
    },
    "payroll": 54639503,
    "team_waa": 7.9,
    "playoffs": false,
    "championship": false
}, {
    "Rk": 25,
    "team_name": "Mariners",
    "Lg": "AL",
    "year": 2004,
    "W": 63,
    "L": 99,
    "W-L%": 0.389,
    "R": 4.3,
    "RA": 5.1,
    "Rdiff": -0.8,
    "SOS": 0.2,
    "SRS": -0.6,
    "pythWL": "69-93",
    "Luck": -6,
    "Inter": "9-9",
    "Home": "38-44",
    "Road": "25-55",
    "ExInn": "11-6",
    "1Run": "20-30",
    "vRHP": "44-68",
    "vLHP": "19-31",
    "≥": {
        "500": "37-66"
    },
    "<": {
        "500": "26-33"
    },
    "payroll": 81543833,
    "team_waa": -7.1,
    "playoffs": false,
    "championship": false
}, {
    "Rk": 26,
    "team_name": "Giants",
    "Lg": "NL",
    "year": 2004,
    "W": 91,
    "L": 71,
    "W-L%": 0.562,
    "R": 5.2,
    "RA": 4.8,
    "Rdiff": 0.5,
    "SOS": -0.2,
    "SRS": 0.3,
    "pythWL": "88-74",
    "Luck": 3,
    "Inter": "11-7",
    "Home": "47-35",
    "Road": "44-36",
    "ExInn": "8-10",
    "1Run": "18-25",
    "vRHP": "59-53",
    "vLHP": "32-18",
    "≥": {
        "500": "44-41"
    },
    "<": {
        "500": "47-30"
    },
    "payroll": 82019167,
    "team_waa": 6.4,
    "playoffs": false,
    "championship": false
}, {
    "Rk": 27,
    "team_name": "Cardinals",
    "Lg": "NL",
    "year": 2004,
    "W": 105,
    "L": 57,
    "W-L%": 0.648,
    "R": 5.3,
    "RA": 4.1,
    "Rdiff": 1.2,
    "SOS": -0.1,
    "SRS": 1.1,
    "pythWL": "100-62",
    "Luck": 5,
    "Inter": "11-1",
    "Home": "53-28",
    "Road": "52-29",
    "ExInn": "9-4",
    "1Run": "29-20",
    "vRHP": "79-44",
    "vLHP": "26-13",
    "≥": {
        "500": "46-33"
    },
    "<": {
        "500": "59-24"
    },
    "payroll": 75633517,
    "team_waa": 19.0,
    "playoffs": true,
    "championship": false
}, {
    "Rk": 28,
    "team_name": "Rays",
    "Lg": "AL",
    "year": 2004,
    "W": 70,
    "L": 91,
    "W-L%": 0.435,
    "R": 4.4,
    "RA": 5.2,
    "Rdiff": -0.8,
    "SOS": 0.1,
    "SRS": -0.7,
    "pythWL": "68-93",
    "Luck": 2,
    "Inter": "15-3",
    "Home": "41-39",
    "Road": "29-52",
    "ExInn": "6-7",
    "1Run": "17-19",
    "vRHP": "45-70",
    "vLHP": "25-21",
    "≥": {
        "500": "30-60"
    },
    "<": {
        "500": "40-31"
    },
    "payroll": 29506667,
    "team_waa": -10.6,
    "playoffs": false,
    "championship": false
}, {
    "Rk": 29,
    "team_name": "Rangers",
    "Lg": "AL",
    "year": 2004,
    "W": 89,
    "L": 73,
    "W-L%": 0.549,
    "R": 5.3,
    "RA": 4.9,
    "Rdiff": 0.4,
    "SOS": 0.1,
    "SRS": 0.5,
    "pythWL": "87-75",
    "Luck": 2,
    "Inter": "10-8",
    "Home": "51-30",
    "Road": "38-43",
    "ExInn": "5-4",
    "1Run": "24-19",
    "vRHP": "60-49",
    "vLHP": "29-24",
    "≥": {
        "500": "40-45"
    },
    "<": {
        "500": "49-28"
    },
    "payroll": 54825973,
    "team_waa": 4.0,
    "playoffs": false,
    "championship": false
}, {
    "Rk": 30,
    "team_name": "Bluejays",
    "Lg": "AL",
    "year": 2004,
    "W": 67,
    "L": 94,
    "W-L%": 0.416,
    "R": 4.5,
    "RA": 5.1,
    "Rdiff": -0.6,
    "SOS": 0.1,
    "SRS": -0.5,
    "pythWL": "71-90",
    "Luck": -4,
    "Inter": "8-10",
    "Home": "40-41",
    "Road": "27-53",
    "ExInn": "4-7",
    "1Run": "17-22",
    "vRHP": "47-65",
    "vLHP": "20-29",
    "≥": {
        "500": "32-55"
    },
    "<": {
        "500": "35-39"
    },
    "payroll": 50017000,
    "team_waa": -8.1,
    "playoffs": false,
    "championship": false
}]
